yt/__init__.py
yt/common.py
yt/json_wrapper.py
yt/logger.py
yt/logger_config.py
yt/subprocess_wrapper.py
yt/cli/__init__.py
yt/cli/command_explain_id.py
yt/cli/strawberry_parser.py
yt/cli/yt_binary.py
yt/clickhouse/__init__.py
yt/clickhouse/clickhouse.py
yt/clickhouse/client.py
yt/clickhouse/compatibility.py
yt/clickhouse/defaults.py
yt/clickhouse/execute.py
yt/clickhouse/helpers.py
yt/clickhouse/log_tailer.py
yt/clickhouse/spec_builder.py
yt/clickhouse/test_helpers.py
yt/packages/__init__.py
yt/packages/expiringdict.py
yt/packages/fuse.py
yt/packages/importlib.py
yt/packages/dill/__diff.py
yt/packages/dill/__init__.py
yt/packages/dill/_dill.py
yt/packages/dill/_objects.py
yt/packages/dill/_shims.py
yt/packages/dill/detect.py
yt/packages/dill/objtypes.py
yt/packages/dill/pointers.py
yt/packages/dill/settings.py
yt/packages/dill/source.py
yt/packages/dill/temp.py
yt/packages/requests/__init__.py
yt/packages/requests/__version__.py
yt/packages/requests/_internal_utils.py
yt/packages/requests/adapters.py
yt/packages/requests/api.py
yt/packages/requests/auth.py
yt/packages/requests/cacert.pem
yt/packages/requests/certs.py
yt/packages/requests/compat.py
yt/packages/requests/cookies.py
yt/packages/requests/exceptions.py
yt/packages/requests/help.py
yt/packages/requests/hooks.py
yt/packages/requests/models.py
yt/packages/requests/packages.py
yt/packages/requests/sessions.py
yt/packages/requests/status_codes.py
yt/packages/requests/structures.py
yt/packages/requests/utils.py
yt/packages/urllib3/__init__.py
yt/packages/urllib3/_collections.py
yt/packages/urllib3/_version.py
yt/packages/urllib3/connection.py
yt/packages/urllib3/connectionpool.py
yt/packages/urllib3/exceptions.py
yt/packages/urllib3/fields.py
yt/packages/urllib3/filepost.py
yt/packages/urllib3/poolmanager.py
yt/packages/urllib3/request.py
yt/packages/urllib3/response.py
yt/packages/urllib3/contrib/__init__.py
yt/packages/urllib3/contrib/_appengine_environ.py
yt/packages/urllib3/contrib/appengine.py
ytsaurus_client-0.13.46.dist-info/METADATA
ytsaurus_client-0.13.46.dist-info/WHEEL
ytsaurus_client-0.13.46.dist-info/entry_points.txt
ytsaurus_client-0.13.46.dist-info/top_level.txt
ytsaurus_client-0.13.46.dist-info/RECORD
